{"layout":"indicator","goal":1,"indicator":"12.4","indicator_display":"12.4","indicator_sort_order":"12-4","permalink":"/12-4/","reporting_status":"complete","published":true,"data_non_statistical":false,"dialogue":"new","color":"966d24","proposal_ressort":"Bundesministerium f\u00fcr Umwelt, Naturschutz, nukleare Sicherheit und Verbraucherschutz (BMUV)<br>Bundeskanzleramt<br>Bundesministerium f\u00fcr Wirtschaft und Klimaschutz (BMWK)<br>Bundesministerium der Finanzen (BMF)","proposal_description_new":"Reduktion der Verbraucherverschuldung in Relation zum BIP","proposal_target":"Reduzierung der Verschuldungsquote auf unter 15 Prozent","national_indicator_available":"Quote der Verbraucherverschuldung","indicator_name":"Quote der Verbraucherverschuldung","section":"Verbraucherverschuldung","postulate":"Verschuldung von Verbraucherinnen und Verbrauchern wirksam eind\u00e4mmen","target_id":"12.4.1","previous":"12-3-abc","next":"13-1-a","graph_target_points":[{"type":"box","xMin":9.7,"xMax":10.3,"yMin":0,"yMax":15,"borderColor":"#966d24","backgroundColor":"transparent","borderDash":[1,0],"borderWidth":2,"preset":"target_points"},{"type":"label","xValue":10,"yValue":18,"backgroundColor":"transparent","content":["Ziel:","unter 15 %"],"font":{"size":14},"borderColor":"transparent"}],"graph_annotations":[{"value":300.5,"label":{"content":"Ziel 2030","position":"left","backgroundColor":"transparent","color":"transparent"},"preset":"target_line","borderColor":"transparent"}],"data_show_map":false,"copyright":"&copy; Statistisches Bundesamt (Destatis), 2024","data_footnote":"\u00b9 Kredite an private Haushalte und private Organisationen ohne Erwerbszweck.","graph_title":"Verschuldung privater Haushalte\u00b9 in Relation zum Bruttoinlandsprodukt","graph_subtitle":"ohne Wohnungsbaukredite","source_active_1":true,"source_organisation_1":"<a href=\"https://www.bundesbank.de/\" target=\"_blank\" onclick=\"return confirm_alert('der Bundesbank', 'De')\">Deutsche Bundesbank</a>","source_organisation_1_short":"<a href=\"https://www.bundesbank.de/\" target=\"_blank\" onclick=\"return confirm_alert('der Bundesbank', 'De')\">Deutsche Bundesbank</a>","source_organisation_logo_1":"<a href=\"https://www.bundesbank.de/\" target=\"_blank\" onclick=\"return confirm_alert('der Bundesbank', 'De')\"><img src=\"https://dns-indikatoren.de/public/OrgImgDe/bundesbank.png\" alt=\"Deutsche Bundesbank\" title=\" Klicken Sie hier um zur Homepage der Organisation Deutsche Bundesbank zu gelangen.\" style=\"height:60px; width:148px; border:transparent\"/></a>","source_url_1":"https://www.bundesbank.de/resource/blob/911812/51843dca8e20a5949cff80859d8458d7/mL/2023-06-21-13-04-11-finanzierungsrechnung-data.pdf","source_url_text_1":"Finanzierungsrechnung","source_url_alert_1":"der Bundesbank","source_active_2":true,"source_organisation_2":"<a href=\"https://www.destatis.de/DE/Home/_inhalt.html\" target=\"_blank\">Statistisches Bundesamt</a>","source_organisation_2_short":"<a href=\"https://www.destatis.de/DE/Home/_inhalt.html\" target=\"_blank\">Statistisches Bundesamt</a>","source_organisation_logo_2":"<a href=\"https://www.destatis.de/DE/Home/_inhalt.html\" target=\"_blank\"><img src=\"https://dns-indikatoren.de/public/OrgImgDe/destatis.png\" alt=\"Statistisches Bundesamt\" title=\" Klicken Sie hier um zur Homepage der Organisation Statistisches Bundesamt zu gelangen.\" style=\"height:60px; width:148px; border:transparent\"/></a>","source_url_2":"https://www-genesis.destatis.de/genesis/online?sequenz=tabelleErgebnis&selectionname=81000-0001#abreadcrumb","source_url_text_2":"VGR des Bundes - Bruttoinlandsprodukt","precision":[{"decimals":1}],"graph_limits":[{"maximum":25}],"span_gaps":true,"show_line":true,"graph_type":"bar","national_geographical_coverage":"Deutschland","page_content":"","national_metadata_updated_date":"2024-06-21","national_data_updated_date":"2024-06-21","indicator_number":"12.4","target_number":"12.4","goal_number":"12"}